{
  "hash": "ef1c7198",
  "configHash": "ec8c6f33",
  "lockfileHash": "bcf6199a",
  "browserHash": "ec8db637",
  "optimized": {
    "vue": {
      "src": "../../../../node_modules/vue/dist/vue.runtime.esm-bundler.js",
      "file": "vue.js",
      "fileHash": "955c33d0",
      "needsInterop": false
    },
    "vitepress > @vue/devtools-api": {
      "src": "../../../../node_modules/@vue/devtools-api/dist/index.js",
      "file": "vitepress___@vue_devtools-api.js",
      "fileHash": "2484c0d5",
      "needsInterop": false
    },
    "vitepress > @vueuse/core": {
      "src": "../../../../node_modules/@vueuse/core/index.mjs",
      "file": "vitepress___@vueuse_core.js",
      "fileHash": "81bde487",
      "needsInterop": false
    },
    "@braintree/sanitize-url": {
      "src": "../../../../node_modules/@braintree/sanitize-url/dist/index.js",
      "file": "@braintree_sanitize-url.js",
      "fileHash": "0a49013f",
      "needsInterop": true
    },
    "dayjs": {
      "src": "../../../../node_modules/dayjs/dayjs.min.js",
      "file": "dayjs.js",
      "fileHash": "6530e732",
      "needsInterop": true
    },
    "debug": {
      "src": "../../../../node_modules/debug/src/browser.js",
      "file": "debug.js",
      "fileHash": "989e018e",
      "needsInterop": true
    },
    "cytoscape-cose-bilkent": {
      "src": "../../../../node_modules/cytoscape-cose-bilkent/cytoscape-cose-bilkent.js",
      "file": "cytoscape-cose-bilkent.js",
      "fileHash": "aa432730",
      "needsInterop": true
    },
    "cytoscape": {
      "src": "../../../../node_modules/cytoscape/dist/cytoscape.esm.mjs",
      "file": "cytoscape.js",
      "fileHash": "32f4a89f",
      "needsInterop": false
    },
    "vitepress > @vueuse/integrations/useFocusTrap": {
      "src": "../../../../node_modules/@vueuse/integrations/useFocusTrap.mjs",
      "file": "vitepress___@vueuse_integrations_useFocusTrap.js",
      "fileHash": "9380c325",
      "needsInterop": false
    },
    "vitepress > mark.js/src/vanilla.js": {
      "src": "../../../../node_modules/mark.js/src/vanilla.js",
      "file": "vitepress___mark__js_src_vanilla__js.js",
      "fileHash": "94b362ec",
      "needsInterop": false
    },
    "vitepress > minisearch": {
      "src": "../../../../node_modules/minisearch/dist/es/index.js",
      "file": "vitepress___minisearch.js",
      "fileHash": "95d8adc5",
      "needsInterop": false
    }
  },
  "chunks": {
    "chunk-R2523JEZ": {
      "file": "chunk-R2523JEZ.js"
    },
    "chunk-LS57BFBI": {
      "file": "chunk-LS57BFBI.js"
    },
    "chunk-BUSYA2B4": {
      "file": "chunk-BUSYA2B4.js"
    }
  }
}